Workbook

Sheet Enunciados
A1: Recuperación – Excel
A2: Diez ejercicios. Trabaja SOLO en las celdas amarillas de cada hoja. Las fórmulas deben quedar a la vista: un valor escrito a mano vale 0.
A3: Leyenda: | B3: Celda a completar | C3: Encabezado naranja = columna que debes calcular
A5: # | B5: Título | C5: Hoja de trabajo | D5: Funciones sugeridas | E5: Dificultad | F5: Enunciado
A6: 1 | B6: Buscar y calcular en Ventas | C6: Ventas | D6: BUSCARX / INDICE+COINCIDIR, SI.ERROR | E6: Media | F6: Completa las columnas amarillas de la hoja Ventas. 'Producto' y 'Precio unitario' salen del Catálogo a partir del código. Ojo: hay códigos que no existen en el catálogo; en esos casos la fila debe mostrar 'CÓDIGO NO EXISTE' en Producto y 0 en precio, sin ningún #N/D a la vista. 'Total' = Cantidad × Precio aplicando el descuento de la categoría del producto (tabla de descuentos en la hoja Catálogo). Una sola fórmula por columna, arrastrada hasta el final.
A7: 2 | B7: Matriz región × mes | C7: E2_Resumen | D7: SUMAR.SI.CONJUNTO, fechas, referencias mixtas | E7: Media-Alta | F7: Construye la matriz de ventas totales por región (filas) y mes (columnas) usando la columna Total de Ventas. Condición: escribes UNA sola fórmula en la celda superior izquierda y la copias a toda la matriz sin editarla (usa bien los $). Agrega totales por fila y por columna, y una columna con el % que representa cada región sobre el total general. Los meses del encabezado son fechas, no texto.
A8: 3 | B8: Comisiones escalonadas y bono | C8: E3_Comisiones | D8: BUSCARV aproximado, SUMAPRODUCTO, SI | E8: Alta | F8: Para cada vendedor calcula: venta total del semestre, % de comisión según la tabla de tramos (búsqueda aproximada, sin SI anidados), valor de la comisión y el bono. El bono es de $500.000 solo si el vendedor superó la meta mensual en al menos 4 de los 6 meses. Resuelve 'meses que superó la meta' con una sola fórmula por vendedor, sin columnas auxiliares (pista: SUMAPRODUCTO o una matriz dinámica).
A9: 4 | B9: Antigüedad y prima | C9: Empleados | D9: SIFECHA, fechas, concatenación, SI.CONJUNTO | E9: Media-Alta | F9: Tomando como fecha de corte la celda indicada en la hoja (no uses HOY()), calcula la antigüedad como texto con el formato '4 años y 7 meses' (si son 0 años debe decir solo '7 meses'). Luego calcula la prima: 0% con menos de 2 años, 5% de 2 a menos de 5, 10% de 5 a menos de 10 y 15% desde 10. Finalmente, la fecha del próximo aniversario laboral posterior a la fecha de corte.
A10: 5 | B10: Limpieza de clientes | C10: Clientes | D10: ESPACIOS, NOMPROPIO, EXTRAE, HALLAR, SUSTITUIR, CONTAR.SI | E10: Alta | F10: Los datos de clientes llegaron sucios. Completa: nombre limpio (sin espacios de más y con mayúscula inicial en cada palabra), primer apellido (segunda palabra del nombre limpio), usuario del correo (lo que va antes de @), dominio (lo que va después de @, en minúscula), teléfono normalizado (solo los 10 dígitos, sin guiones, espacios, paréntesis ni +57) y una columna 'Duplicado' que diga SÍ cuando el correo aparece más de una vez sin importar mayúsculas o espacios.
A11: 6 | B11: Ranking con empates | C11: E6_Ranking | D11: K.ESIMO.MAYOR, INDICE, COINCIDIR / ORDENAR, FILTRAR | E11: Alta | F11: Usando la hoja Ventas, arma el Top 3 de vendedores por venta total y el Top 3 de productos por unidades vendidas. Debe funcionar aunque haya empates (dos vendedores con el mismo total no pueden aparecer como el mismo nombre repetido). Si cambio un dato en Ventas, el ranking se actualiza solo.
A12: 7 | B12: Entregas y días hábiles | C12: Pedidos | D12: DIA.LAB, DIAS.LAB, festivos, SI anidado | E12: Media-Alta | F12: Para cada pedido calcula la fecha límite de entrega sumando el plazo en días hábiles a la fecha de pedido, excluyendo sábados, domingos y los festivos de la hoja Festivos. Luego los días hábiles que tardó la entrega real y el estado: 'Pendiente' si no hay fecha de entrega, 'Retrasado' si se entregó después de la fecha límite, 'A tiempo' en otro caso. Al final, cuenta cuántos pedidos retrasados tiene cada región.
A13: 8 | B13: Controles visuales | C13: Catálogo y Ventas | D13: Formato condicional con fórmula, validación de datos | E13: Media | F13: En Catálogo: resalta en rojo la FILA COMPLETA de los productos cuyo stock está por debajo del stock mínimo y en amarillo los que están a menos de 5 unidades de llegar al mínimo (usa formato condicional con fórmula, no el de reglas predefinidas). En Ventas: aplica validación de datos a la columna Código para que solo se puedan elegir códigos del Catálogo desde una lista, con un mensaje de error personalizado.
A14: 9 | B14: Panel interactivo | C14: E9_Panel | D14: Validación de datos, SUMAR.SI.CONJUNTO, INDICE/COINCIDIR, formato condicional | E14: Alta | F14: Crea dos listas desplegables: vendedor y mes. Según lo que se elija, el panel debe mostrar: venta total, unidades vendidas, número de transacciones, ticket promedio, producto más vendido (en unidades) y la variación % frente al mes anterior. Si el mes elegido es enero, la variación debe mostrar 'N/A'. Pon la variación en verde si es positiva y en rojo si es negativa.
A15: 10 | B15: Tabla de amortización | C15: E10_Credito | D15: PAGO, tasas equivalentes, referencias absolutas | E15: Alta | F15: Con los datos del crédito de la hoja, convierte la tasa efectiva anual a tasa mensual equivalente (no dividas entre 12). Calcula la cuota fija con PAGO y construye la tabla completa: cuota, interés, abono a capital y saldo. El saldo del último mes debe dar 0. Después, en el escenario B, simula un abono extraordinario en el mes indicado y calcula cuántos meses se ahorra y cuánto dinero en intereses.

Sheet Catálogo
A1: Catálogo de productos
A2: Datos base para los ejercicios 1 y 8.
A4: Código | B4: Producto | C4: Categoría | D4: Precio unitario | E4: Stock | F4: Stock mínimo | I4: Descuentos por categoría
A5: P-101 | B5: Teclado mecánico | C5: Periféricos | D5: 185000 | E5: 34 | F5: 20 | I5: Categoría | J5: Descuento
A6: P-102 | B6: Mouse inalámbrico | C6: Periféricos | D6: 72000 | E6: 12 | F6: 15 | I6: Periféricos | J6: 0.05
A7: P-103 | B7: Monitor 24" | C7: Pantallas | D7: 690000 | E7: 8 | F7: 10 | I7: Pantallas | J7: 0.08
A8: P-104 | B8: Monitor 27" | C8: Pantallas | D8: 1150000 | E8: 22 | F8: 6 | I8: Equipos | J8: 0.1
A9: P-105 | B9: Portátil 14" | C9: Equipos | D9: 3200000 | E9: 5 | F9: 4 | I9: Audio | J9: 0
A10: P-106 | B10: Portátil 16" | C10: Equipos | D10: 4550000 | E10: 3 | F10: 4 | I10: Almacenamiento | J10: 0.03
A11: P-107 | B11: Diadema USB | C11: Audio | D11: 145000 | E11: 40 | F11: 15 | I11: Accesorios | J11: 0.12
A12: P-108 | B12: Parlantes 2.1 | C12: Audio | D12: 230000 | E12: 18 | F12: 10
A13: P-109 | B13: Disco SSD 1TB | C13: Almacenamiento | D13: 390000 | E13: 9 | F13: 12
A14: P-110 | B14: Memoria USB 128GB | C14: Almacenamiento | D14: 58000 | E14: 60 | F14: 25
A15: P-111 | B15: Cámara web HD | C15: Periféricos | D15: 165000 | E15: 14 | F15: 10
A16: P-112 | B16: Base refrigerante | C16: Accesorios | D16: 89000 | E16: 7 | F16: 8

Sheet Ventas
A1: Registro de ventas – primer semestre 2026
A2: Ejercicio 1 (columnas naranjas). También es la fuente de los ejercicios 2, 3, 6 y 9.
A4: ID | B4: Fecha | C4: Vendedor | D4: Región | E4: Código | F4: Cantidad | G4: Producto | H4: Precio unitario | I4: Total
A5: V-001 | B5: 46025 | C5: Andrés Ruiz | D5: Caribe | E5: P-107 | F5: 5 | G5: =IFERROR(INDEX(Catálogo!$B$5:$B$16,MATCH(E5,Catálogo!$A$5:$A$16,0)),"CÓDIGO NO EXISTE") -> Diadema USB | H5: =IFERROR(INDEX(Catálogo!$D$5:$D$16,MATCH(E5,Catálogo!$A$5:$A$16,0)),0) -> 145000 | I5: =IF(OR(H5=0,G5="CÓDIGO NO EXISTE"),0,F5*H5*(1-IFERROR(VLOOKUP(INDEX(Catálogo!$C$5:$C$16,MATCH(E5,Catálogo!$A$5:$A$16,0)),Catálogo!$I$6:$J$11,2,FALSE()),0))) -> 725000
A6: V-002 | B6: 46029 | C6: Felipe Rojas | D6: Andina | E6: P-106 | F6: 2 | G6: =IFERROR(INDEX(Catálogo!$B$5:$B$16,MATCH(E6,Catálogo!$A$5:$A$16,0)),"CÓDIGO NO EXISTE") -> Portátil 16" | H6: =IFERROR(INDEX(Catálogo!$D$5:$D$16,MATCH(E6,Catálogo!$A$5:$A$16,0)),0) -> 4550000 | I6: =IF(OR(H6=0,G6="CÓDIGO NO EXISTE"),0,F6*H6*(1-IFERROR(VLOOKUP(INDEX(Catálogo!$C$5:$C$16,MATCH(E6,Catálogo!$A$5:$A$16,0)),Catálogo!$I$6:$J$11,2,FALSE()),0))) -> 8190000
A7: V-003 | B7: 46031 | C7: Andrés Ruiz | D7: Caribe | E7: P-110 | F7: 4 | G7: =IFERROR(INDEX(Catálogo!$B$5:$B$16,MATCH(E7,Catálogo!$A$5:$A$16,0)),"CÓDIGO NO EXISTE") -> Memoria USB 128GB | H7: =IFERROR(INDEX(Catálogo!$D$5:$D$16,MATCH(E7,Catálogo!$A$5:$A$16,0)),0) -> 58000 | I7: =IF(OR(H7=0,G7="CÓDIGO NO EXISTE"),0,F7*H7*(1-IFERROR(VLOOKUP(INDEX(Catálogo!$C$5:$C$16,MATCH(E7,Catálogo!$A$5:$A$16,0)),Catálogo!$I$6:$J$11,2,FALSE()),0))) -> 225040
A8: V-004 | B8: 46031 | C8: Laura Gómez | D8: Andina | E8: P-105 | F8: 4 | G8: =IFERROR(INDEX(Catálogo!$B$5:$B$16,MATCH(E8,Catálogo!$A$5:$A$16,0)),"CÓDIGO NO EXISTE") -> Portátil 14" | H8: =IFERROR(INDEX(Catálogo!$D$5:$D$16,MATCH(E8,Catálogo!$A$5:$A$16,0)),0) -> 3200000 | I8: =IF(OR(H8=0,G8="CÓDIGO NO EXISTE"),0,F8*H8*(1-IFERROR(VLOOKUP(INDEX(Catálogo!$C$5:$C$16,MATCH(E8,Catálogo!$A$5:$A$16,0)),Catálogo!$I$6:$J$11,2,FALSE()),0))) -> 11520000
A9: V-005 | B9: 46034 | C9: Laura Gómez | D9: Andina | E9: P-109 | F9: 5 | G9: =IFERROR(INDEX(Catálogo!$B$5:$B$16,MATCH(E9,Catálogo!$A$5:$A$16,0)),"CÓDIGO NO EXISTE") -> Disco SSD 1TB | H9: =IFERROR(INDEX(Catálogo!$D$5:$D$16,MATCH(E9,Catálogo!$A$5:$A$16,0)),0) -> 390000 | I9: =IF(OR(H9=0,G9="CÓDIGO NO EXISTE"),0,F9*H9*(1-IFERROR(VLOOKUP(INDEX(Catálogo!$C$5:$C$16,MATCH(E9,Catálogo!$A$5:$A$16,0)),Catálogo!$I$6:$J$11,2,FALSE()),0))) -> 1891500
A10: V-006 | B10: 46036 | C10: Laura Gómez | D10: Andina | E10: P-109 | F10: 1 | G10: =IFERROR(INDEX(Catálogo!$B$5:$B$16,MATCH(E10,Catálogo!$A$5:$A$16,0)),"CÓDIGO NO EXISTE") -> Disco SSD 1TB | H10: =IFERROR(INDEX(Catálogo!$D$5:$D$16,MATCH(E10,Catálogo!$A$5:$A$16,0)),0) -> 390000 | I10: =IF(OR(H10=0,G10="CÓDIGO NO EXISTE"),0,F10*H10*(1-IFERROR(VLOOKUP(INDEX(Catálogo!$C$5:$C$16,MATCH(E10,Catálogo!$A$5:$A$16,0)),Catálogo!$I$6:$J$11,2,FALSE()),0))) -> 378300
A11: V-007 | B11: 46040 | C11: Valentina Díaz | D11: Orinoquía | E11: P-101 | F11: 5 | G11: =IFERROR(INDEX(Catálogo!$B$5:$B$16,MATCH(E11,Catálogo!$A$5:$A$16,0)),"CÓDIGO NO EXISTE") -> Teclado mecánico | H11: =IFERROR(INDEX(Catálogo!$D$5:$D$16,MATCH(E11,Catálogo!$A$5:$A$16,0)),0) -> 185000 | I11: =IF(OR(H11=0,G11="CÓDIGO NO EXISTE"),0,F11*H11*(1-IFERROR(VLOOKUP(INDEX(Catálogo!$C$5:$C$16,MATCH(E11,Catálogo!$A$5:$A$16,0)),Catálogo!$I$6:$J$11,2,FALSE()),0))) -> 878750
A12: V-008 | B12: 46041 | C12: Laura Gómez | D12: Andina | E12: P-105 | F12: 4 | G12: =IFERROR(INDEX(Catálogo!$B$5:$B$16,MATCH(E12,Catálogo!$A$5:$A$16,0)),"CÓDIGO NO EXISTE") -> Portátil 14" | H12: =IFERROR(INDEX(Catálogo!$D$5:$D$16,MATCH(E12,Catálogo!$A$5:$A$16,0)),0) -> 3200000 | I12: =IF(OR(H12=0,G12="CÓDIGO NO EXISTE"),0,F12*H12*(1-IFERROR(VLOOKUP(INDEX(Catálogo!$C$5:$C$16,MATCH(E12,Catálogo!$A$5:$A$16,0)),Catálogo!$I$6:$J$11,2,FALSE()),0))) -> 11520000
A13: V-009 | B13: 46044 | C13: Andrés Ruiz | D13: Caribe | E13: P-108 | F13: 4 | G13: =IFERROR(INDEX(Catálogo!$B$5:$B$16,MATCH(E13,Catálogo!$A$5:$A$16,0)),"CÓDIGO NO EXISTE") -> Parlantes 2.1 | H13: =IFERROR(INDEX(Catálogo!$D$5:$D$16,MATCH(E13,Catálogo!$A$5:$A$16,0)),0) -> 230000 | I13: =IF(OR(H13=0,G13="CÓDIGO NO EXISTE"),0,F13*H13*(1-IFERROR(VLOOKUP(INDEX(Catálogo!$C$5:$C$16,MATCH(E13,Catálogo!$A$5:$A$16,0)),Catálogo!$I$6:$J$11,2,FALSE()),0))) -> 920000
A14: V-010 | B14: 46045 | C14: Andrés Ruiz | D14: Caribe | E14: P-103 | F14: 2 | G14: =IFERROR(INDEX(Catálogo!$B$5:$B$16,MATCH(E14,Catálogo!$A$5:$A$16,0)),"CÓDIGO NO EXISTE") -> Monitor 24" | H14: =IFERROR(INDEX(Catálogo!$D$5:$D$16,MATCH(E14,Catálogo!$A$5:$A$16,0)),0) -> 690000 | I14: =IF(OR(H14=0,G14="CÓDIGO NO EXISTE"),0,F14*H14*(1-IFERROR(VLOOKUP(INDEX(Catálogo!$C$5:$C$16,MATCH(E14,Catálogo!$A$5:$A$16,0)),Catálogo!$I$6:$J$11,2,FALSE()),0))) -> 1269600
A15: V-011 | B15: 46045 | C15: Andrés Ruiz | D15: Caribe | E15: P-103 | F15: 2 | G15: =IFERROR(INDEX(Catálogo!$B$5:$B$16,MATCH(E15,Catálogo!$A$5:$A$16,0)),"CÓDIGO NO EXISTE") -> Monitor 24" | H15: =IFERROR(INDEX(Catálogo!$D$5:$D$16,MATCH(E15,Catálogo!$A$5:$A$16,0)),0) -> 690000 | I15: =IF(OR(H15=0,G15="CÓDIGO NO EXISTE"),0,F15*H15*(1-IFERROR(VLOOKUP(INDEX(Catálogo!$C$5:$C$16,MATCH(E15,Catálogo!$A$5:$A$16,0)),Catálogo!$I$6:$J$11,2,FALSE()),0))) -> 1269600
A16: V-012 | B16: 46050 | C16: Valentina Díaz | D16: Orinoquía | E16: P-110 | F16: 6 | G16: =IFERROR(INDEX(Catálogo!$B$5:$B$16,MATCH(E16,Catálogo!$A$5:$A$16,0)),"CÓDIGO NO EXISTE") -> Memoria USB 128GB | H16: =IFERROR(INDEX(Catálogo!$D$5:$D$16,MATCH(E16,Catálogo!$A$5:$A$16,0)),0) -> 58000 | I16: =IF(OR(H16=0,G16="CÓDIGO NO EXISTE"),0,F16*H16*(1-IFERROR(VLOOKUP(INDEX(Catálogo!$C$5:$C$16,MATCH(E16,Catálogo!$A$5:$A$16,0)),Catálogo!$I$6:$J$11,2,FALSE()),0))) -> 337560
... A84: V-080 | B84: 46202 | C84: Laura Gómez | D84: Andina | E84: P-101 | F84: 6 | G84: =IFERROR(INDEX(Catálogo!$B$5:$B$16,MATCH(E84,Catálogo!$A$5:$A$16,0)),"CÓDIGO NO EXISTE") -> Teclado mecánico | H84: =IFERROR(INDEX(Catálogo!$D$5:$D$16,MATCH(E84,Catálogo!$A$5:$A$16,0)),0) -> 185000 | I84: =IF(OR(H84=0,G84="CÓDIGO NO EXISTE"),0,F84*H84*(1-IFERROR(VLOOKUP(INDEX(Catálogo!$C$5:$C$16,MATCH(E84,Catálogo!$A$5:$A$16,0)),Catálogo!$I$6:$J$11,2,FALSE()),0))) -> 1054500

Sheet E2_Resumen
A1: Ejercicio 2 – Ventas por región y mes
A2: Una sola fórmula en B5, copiada a toda la matriz.
A4: Región | B4: 46023 | C4: 46054 | D4: 46082 | E4: 46113 | F4: 46143 | G4: 46174 | H4: Total | I4: % del total
A5: Andina | B5: =SUMIFS(Ventas!$I$5:$I$84,Ventas!$D$5:$D$84,$A5,Ventas!$B$5:$B$84,">="&B$4,Ventas!$B$5:$B$84,"<"&DATE(YEAR(B$4),MONTH(B$4)+1,1)) -> 33499800 | C5: =SUMIFS(Ventas!$I$5:$I$84,Ventas!$D$5:$D$84,$A5,Ventas!$B$5:$B$84,">="&C$4,Ventas!$B$5:$B$84,"<"&DATE(YEAR(C$4),MONTH(C$4)+1,1)) -> 3596550 | D5: =SUMIFS(Ventas!$I$5:$I$84,Ventas!$D$5:$D$84,$A5,Ventas!$B$5:$B$84,">="&D$4,Ventas!$B$5:$B$84,"<"&DATE(YEAR(D$4),MONTH(D$4)+1,1)) -> 2076650 | E5: =SUMIFS(Ventas!$I$5:$I$84,Ventas!$D$5:$D$84,$A5,Ventas!$B$5:$B$84,">="&E$4,Ventas!$B$5:$B$84,"<"&DATE(YEAR(E$4),MONTH(E$4)+1,1)) -> 7608400 | F5: =SUMIFS(Ventas!$I$5:$I$84,Ventas!$D$5:$D$84,$A5,Ventas!$B$5:$B$84,">="&F$4,Ventas!$B$5:$B$84,"<"&DATE(YEAR(F$4),MONTH(F$4)+1,1)) -> 3794950 | G5: =SUMIFS(Ventas!$I$5:$I$84,Ventas!$D$5:$D$84,$A5,Ventas!$B$5:$B$84,">="&G$4,Ventas!$B$5:$B$84,"<"&DATE(YEAR(G$4),MONTH(G$4)+1,1)) -> 4062900 | H5: =SUM(B5:G5) -> 54639250 | I5: =IF($H$9=0,0,H5/$H$9) -> 0.40341179
A6: Caribe | B6: =SUMIFS(Ventas!$I$5:$I$84,Ventas!$D$5:$D$84,$A6,Ventas!$B$5:$B$84,">="&B$4,Ventas!$B$5:$B$84,"<"&DATE(YEAR(B$4),MONTH(B$4)+1,1)) -> 4409240 | C6: =SUMIFS(Ventas!$I$5:$I$84,Ventas!$D$5:$D$84,$A6,Ventas!$B$5:$B$84,">="&C$4,Ventas!$B$5:$B$84,"<"&DATE(YEAR(C$4),MONTH(C$4)+1,1)) -> 1282500 | D6: =SUMIFS(Ventas!$I$5:$I$84,Ventas!$D$5:$D$84,$A6,Ventas!$B$5:$B$84,">="&D$4,Ventas!$B$5:$B$84,"<"&DATE(YEAR(D$4),MONTH(D$4)+1,1)) -> 2294120 | E6: =SUMIFS(Ventas!$I$5:$I$84,Ventas!$D$5:$D$84,$A6,Ventas!$B$5:$B$84,">="&E$4,Ventas!$B$5:$B$84,"<"&DATE(YEAR(E$4),MONTH(E$4)+1,1)) -> 205200 | F6: =SUMIFS(Ventas!$I$5:$I$84,Ventas!$D$5:$D$84,$A6,Ventas!$B$5:$B$84,">="&F$4,Ventas!$B$5:$B$84,"<"&DATE(YEAR(F$4),MONTH(F$4)+1,1)) -> 11898300 | G6: =SUMIFS(Ventas!$I$5:$I$84,Ventas!$D$5:$D$84,$A6,Ventas!$B$5:$B$84,">="&G$4,Ventas!$B$5:$B$84,"<"&DATE(YEAR(G$4),MONTH(G$4)+1,1)) -> 9343000 | H6: =SUM(B6:G6) -> 29432360 | I6: =IF($H$9=0,0,H6/$H$9) -> 0.21730461
A7: Pacífico | B7: =SUMIFS(Ventas!$I$5:$I$84,Ventas!$D$5:$D$84,$A7,Ventas!$B$5:$B$84,">="&B$4,Ventas!$B$5:$B$84,"<"&DATE(YEAR(B$4),MONTH(B$4)+1,1)) -> 0 | C7: =SUMIFS(Ventas!$I$5:$I$84,Ventas!$D$5:$D$84,$A7,Ventas!$B$5:$B$84,">="&C$4,Ventas!$B$5:$B$84,"<"&DATE(YEAR(C$4),MONTH(C$4)+1,1)) -> 4863300 | D7: =SUMIFS(Ventas!$I$5:$I$84,Ventas!$D$5:$D$84,$A7,Ventas!$B$5:$B$84,">="&D$4,Ventas!$B$5:$B$84,"<"&DATE(YEAR(D$4),MONTH(D$4)+1,1)) -> 1614960 | E7: =SUMIFS(Ventas!$I$5:$I$84,Ventas!$D$5:$D$84,$A7,Ventas!$B$5:$B$84,">="&E$4,Ventas!$B$5:$B$84,"<"&DATE(YEAR(E$4),MONTH(E$4)+1,1)) -> 6966260 | F7: =SUMIFS(Ventas!$I$5:$I$84,Ventas!$D$5:$D$84,$A7,Ventas!$B$5:$B$84,">="&F$4,Ventas!$B$5:$B$84,"<"&DATE(YEAR(F$4),MONTH(F$4)+1,1)) -> 8722430 | G7: =SUMIFS(Ventas!$I$5:$I$84,Ventas!$D$5:$D$84,$A7,Ventas!$B$5:$B$84,">="&G$4,Ventas!$B$5:$B$84,"<"&DATE(YEAR(G$4),MONTH(G$4)+1,1)) -> 20885400 | H7: =SUM(B7:G7) -> 43052350 | I7: =IF($H$9=0,0,H7/$H$9) -> 0.31786354
A8: Orinoquía | B8: =SUMIFS(Ventas!$I$5:$I$84,Ventas!$D$5:$D$84,$A8,Ventas!$B$5:$B$84,">="&B$4,Ventas!$B$5:$B$84,"<"&DATE(YEAR(B$4),MONTH(B$4)+1,1)) -> 1216310 | C8: =SUMIFS(Ventas!$I$5:$I$84,Ventas!$D$5:$D$84,$A8,Ventas!$B$5:$B$84,">="&C$4,Ventas!$B$5:$B$84,"<"&DATE(YEAR(C$4),MONTH(C$4)+1,1)) -> 4192560 | D8: =SUMIFS(Ventas!$I$5:$I$84,Ventas!$D$5:$D$84,$A8,Ventas!$B$5:$B$84,">="&D$4,Ventas!$B$5:$B$84,"<"&DATE(YEAR(D$4),MONTH(D$4)+1,1)) -> 1630500 | E8: =SUMIFS(Ventas!$I$5:$I$84,Ventas!$D$5:$D$84,$A8,Ventas!$B$5:$B$84,">="&E$4,Ventas!$B$5:$B$84,"<"&DATE(YEAR(E$4),MONTH(E$4)+1,1)) -> 1223280 | F8: =SUMIFS(Ventas!$I$5:$I$84,Ventas!$D$5:$D$84,$A8,Ventas!$B$5:$B$84,">="&F$4,Ventas!$B$5:$B$84,"<"&DATE(YEAR(F$4),MONTH(F$4)+1,1)) -> 56260 | G8: =SUMIFS(Ventas!$I$5:$I$84,Ventas!$D$5:$D$84,$A8,Ventas!$B$5:$B$84,">="&G$4,Ventas!$B$5:$B$84,"<"&DATE(YEAR(G$4),MONTH(G$4)+1,1)) -> 0 | H8: =SUM(B8:G8) -> 8318910 | I8: =IF($H$9=0,0,H8/$H$9) -> 0.061420066
A9: Total | B9: =SUM(B5:B8) -> 39125350 | C9: =SUM(C5:C8) -> 13934910 | D9: =SUM(D5:D8) -> 7616230 | E9: =SUM(E5:E8) -> 16003140 | F9: =SUM(F5:F8) -> 24471940 | G9: =SUM(G5:G8) -> 34291300 | H9: =SUM(H5:H8) -> 135442870

Sheet E3_Comisiones
A1: Ejercicio 3 – Comisiones del semestre
A3: Meta mensual por vendedor: | C3: 4000000
A5: Vendedor | B5: Venta semestre | C5: % comisión | D5: Comisión | E5: Meses sobre la meta | F5: Bono | G5: Total a pagar | J5: Tabla de tramos
A6: Laura Gómez | B6: =SUMIF(Ventas!$C$5:$C$84,A6,Ventas!$I$5:$I$84) -> 36026260 | C6: =VLOOKUP(B6,$J$7:$K$11,2,TRUE()) -> 0.05 | D6: =B6*C6 -> 1801313 | E6: =--(SUMIFS(Ventas!$I$5:$I$84,Ventas!$C$5:$C$84,A6,Ventas!$B$5:$B$84,">="&DATE(2026,1,1),Ventas!$B$5:$B$84,"<"&DATE(2026,2,1))>$C$3)+--(SUMIFS(Ventas!$I$5:$I$84,Ventas!$C$5:$C$84,A6,Ventas!$B$5:$B$84,">="&DATE(2026,2,1),Ventas!$B$5:$B$84,"<"&DATE(2026,3,1))>$C$3)+--(SUMIFS(Ventas!$I$5:$I$84,Ventas!$C$5:$C$84,A6,Ventas!$B$5:$B$84,">="&DATE(2026,3,1),Ventas!$B$5:$B$84,"<"&DATE(2026,4,1))>$C$3)+--(SUMIFS(Ventas!$I$5:$I$84,Ventas!$C$5:$C$84,A6,Ventas!$B$5:$B$84,">="&DATE(2026,4,1),Ventas!$B$5:$B$84,"<"&DATE(2026,5,1))>$C$3)+--(SUMIFS(Ventas!$I$5:$I$84,Ventas!$C$5:$C$84,A6,Ventas!$B$5:$B$84,">="&DATE(2026,5,1),Ventas!$B$5:$B$84,"<"&DATE(2026,6,1))>$C$3)+--(SUMIFS(Ventas!$I$5:$I$84,Ventas!$C$5:$C$84,A6,Ventas!$B$5:$B$84,">="&DATE(2026,6,1),Ventas!$B$5:$B$84,"<"&DATE(2026,7,1))>$C$3) -> 2 | F6: =IF(E6>=4,500000,0) -> 0 | G6: =D6+F6 -> 1801313 | J6: Venta desde | K6: % comisión
A7: Andrés Ruiz | B7: =SUMIF(Ventas!$C$5:$C$84,A7,Ventas!$I$5:$I$84) -> 29432360 | C7: =VLOOKUP(B7,$J$7:$K$11,2,TRUE()) -> 0.035 | D7: =B7*C7 -> 1030132.6 | E7: =--(SUMIFS(Ventas!$I$5:$I$84,Ventas!$C$5:$C$84,A7,Ventas!$B$5:$B$84,">="&DATE(2026,1,1),Ventas!$B$5:$B$84,"<"&DATE(2026,2,1))>$C$3)+--(SUMIFS(Ventas!$I$5:$I$84,Ventas!$C$5:$C$84,A7,Ventas!$B$5:$B$84,">="&DATE(2026,2,1),Ventas!$B$5:$B$84,"<"&DATE(2026,3,1))>$C$3)+--(SUMIFS(Ventas!$I$5:$I$84,Ventas!$C$5:$C$84,A7,Ventas!$B$5:$B$84,">="&DATE(2026,3,1),Ventas!$B$5:$B$84,"<"&DATE(2026,4,1))>$C$3)+--(SUMIFS(Ventas!$I$5:$I$84,Ventas!$C$5:$C$84,A7,Ventas!$B$5:$B$84,">="&DATE(2026,4,1),Ventas!$B$5:$B$84,"<"&DATE(2026,5,1))>$C$3)+--(SUMIFS(Ventas!$I$5:$I$84,Ventas!$C$5:$C$84,A7,Ventas!$B$5:$B$84,">="&DATE(2026,5,1),Ventas!$B$5:$B$84,"<"&DATE(2026,6,1))>$C$3)+--(SUMIFS(Ventas!$I$5:$I$84,Ventas!$C$5:$C$84,A7,Ventas!$B$5:$B$84,">="&DATE(2026,6,1),Ventas!$B$5:$B$84,"<"&DATE(2026,7,1))>$C$3) -> 3 | F7: =IF(E7>=4,500000,0) -> 0 | G7: =D7+F7 -> 1030132.6 | J7: 0 | K7: 0.01
A8: Camila Torres | B8: =SUMIF(Ventas!$C$5:$C$84,A8,Ventas!$I$5:$I$84) -> 43052350 | C8: =VLOOKUP(B8,$J$7:$K$11,2,TRUE()) -> 0.05 | D8: =B8*C8 -> 2152617.5 | E8: =--(SUMIFS(Ventas!$I$5:$I$84,Ventas!$C$5:$C$84,A8,Ventas!$B$5:$B$84,">="&DATE(2026,1,1),Ventas!$B$5:$B$84,"<"&DATE(2026,2,1))>$C$3)+--(SUMIFS(Ventas!$I$5:$I$84,Ventas!$C$5:$C$84,A8,Ventas!$B$5:$B$84,">="&DATE(2026,2,1),Ventas!$B$5:$B$84,"<"&DATE(2026,3,1))>$C$3)+--(SUMIFS(Ventas!$I$5:$I$84,Ventas!$C$5:$C$84,A8,Ventas!$B$5:$B$84,">="&DATE(2026,3,1),Ventas!$B$5:$B$84,"<"&DATE(2026,4,1))>$C$3)+--(SUMIFS(Ventas!$I$5:$I$84,Ventas!$C$5:$C$84,A8,Ventas!$B$5:$B$84,">="&DATE(2026,4,1),Ventas!$B$5:$B$84,"<"&DATE(2026,5,1))>$C$3)+--(SUMIFS(Ventas!$I$5:$I$84,Ventas!$C$5:$C$84,A8,Ventas!$B$5:$B$84,">="&DATE(2026,5,1),Ventas!$B$5:$B$84,"<"&DATE(2026,6,1))>$C$3)+--(SUMIFS(Ventas!$I$5:$I$84,Ventas!$C$5:$C$84,A8,Ventas!$B$5:$B$84,">="&DATE(2026,6,1),Ventas!$B$5:$B$84,"<"&DATE(2026,7,1))>$C$3) -> 4 | F8: =IF(E8>=4,500000,0) -> 500000 | G8: =D8+F8 -> 2652617.5 | J8: 10000000 | K8: 0.02
A9: Felipe Rojas | B9: =SUMIF(Ventas!$C$5:$C$84,A9,Ventas!$I$5:$I$84) -> 18612990 | C9: =VLOOKUP(B9,$J$7:$K$11,2,TRUE()) -> 0.02 | D9: =B9*C9 -> 372259.8 | E9: =--(SUMIFS(Ventas!$I$5:$I$84,Ventas!$C$5:$C$84,A9,Ventas!$B$5:$B$84,">="&DATE(2026,1,1),Ventas!$B$5:$B$84,"<"&DATE(2026,2,1))>$C$3)+--(SUMIFS(Ventas!$I$5:$I$84,Ventas!$C$5:$C$84,A9,Ventas!$B$5:$B$84,">="&DATE(2026,2,1),Ventas!$B$5:$B$84,"<"&DATE(2026,3,1))>$C$3)+--(SUMIFS(Ventas!$I$5:$I$84,Ventas!$C$5:$C$84,A9,Ventas!$B$5:$B$84,">="&DATE(2026,3,1),Ventas!$B$5:$B$84,"<"&DATE(2026,4,1))>$C$3)+--(SUMIFS(Ventas!$I$5:$I$84,Ventas!$C$5:$C$84,A9,Ventas!$B$5:$B$84,">="&DATE(2026,4,1),Ventas!$B$5:$B$84,"<"&DATE(2026,5,1))>$C$3)+--(SUMIFS(Ventas!$I$5:$I$84,Ventas!$C$5:$C$84,A9,Ventas!$B$5:$B$84,">="&DATE(2026,5,1),Ventas!$B$5:$B$84,"<"&DATE(2026,6,1))>$C$3)+--(SUMIFS(Ventas!$I$5:$I$84,Ventas!$C$5:$C$84,A9,Ventas!$B$5:$B$84,">="&DATE(2026,6,1),Ventas!$B$5:$B$84,"<"&DATE(2026,7,1))>$C$3) -> 1 | F9: =IF(E9>=4,500000,0) -> 0 | G9: =D9+F9 -> 372259.8 | J9: 20000000 | K9: 0.035
A10: Valentina Díaz | B10: =SUMIF(Ventas!$C$5:$C$84,A10,Ventas!$I$5:$I$84) -> 8318910 | C10: =VLOOKUP(B10,$J$7:$K$11,2,TRUE()) -> 0.01 | D10: =B10*C10 -> 83189.1 | E10: =--(SUMIFS(Ventas!$I$5:$I$84,Ventas!$C$5:$C$84,A10,Ventas!$B$5:$B$84,">="&DATE(2026,1,1),Ventas!$B$5:$B$84,"<"&DATE(2026,2,1))>$C$3)+--(SUMIFS(Ventas!$I$5:$I$84,Ventas!$C$5:$C$84,A10,Ventas!$B$5:$B$84,">="&DATE(2026,2,1),Ventas!$B$5:$B$84,"<"&DATE(2026,3,1))>$C$3)+--(SUMIFS(Ventas!$I$5:$I$84,Ventas!$C$5:$C$84,A10,Ventas!$B$5:$B$84,">="&DATE(2026,3,1),Ventas!$B$5:$B$84,"<"&DATE(2026,4,1))>$C$3)+--(SUMIFS(Ventas!$I$5:$I$84,Ventas!$C$5:$C$84,A10,Ventas!$B$5:$B$84,">="&DATE(2026,4,1),Ventas!$B$5:$B$84,"<"&DATE(2026,5,1))>$C$3)+--(SUMIFS(Ventas!$I$5:$I$84,Ventas!$C$5:$C$84,A10,Ventas!$B$5:$B$84,">="&DATE(2026,5,1),Ventas!$B$5:$B$84,"<"&DATE(2026,6,1))>$C$3)+--(SUMIFS(Ventas!$I$5:$I$84,Ventas!$C$5:$C$84,A10,Ventas!$B$5:$B$84,">="&DATE(2026,6,1),Ventas!$B$5:$B$84,"<"&DATE(2026,7,1))>$C$3) -> 1 | F10: =IF(E10>=4,500000,0) -> 0 | G10: =D10+F10 -> 83189.1 | J10: 35000000 | K10: 0.05
J11: 50000000 | K11: 0.07

Sheet Empleados
A1: Ejercicio 4 – Antigüedad y prima
A3: Fecha de corte: | B3: 46203
A5: Nombre | B5: Cargo | C5: Fecha de ingreso | D5: Salario base | E5: Antigüedad (texto) | F5: % prima | G5: Valor prima | H5: Próximo aniversario
A6: Sofía Márquez | B6: Analista | C6: 44515 | D6: 3800000 | E6: =IF(DATEDIF(C6,$B$3,"Y")=0,DATEDIF(C6,$B$3,"M")&" meses",DATEDIF(C6,$B$3,"Y")&" años y "&DATEDIF(C6,$B$3,"YM")&" meses") -> 4 años y 7 meses | F6: =IF(DATEDIF(C6,$B$3,"Y")<2,0,IF(DATEDIF(C6,$B$3,"Y")<5,0.05,IF(DATEDIF(C6,$B$3,"Y")<10,0.1,0.15))) -> 0.05 | G6: =D6*F6 -> 190000 | H6: =IF(DATE(YEAR($B$3),MONTH(C6),MIN(DAY(C6),DAY(DATE(YEAR($B$3),MONTH(C6)+1,0))))>$B$3,DATE(YEAR($B$3),MONTH(C6),MIN(DAY(C6),DAY(DATE(YEAR($B$3),MONTH(C6)+1,0)))),DATE(YEAR($B$3)+1,MONTH(C6),MIN(DAY(C6),DAY(DATE(YEAR($B$3)+1,MONTH(C6)+1,0))))) -> 46341
A7: Julián Herrera | B7: Coordinador | C7: 41700 | D7: 6200000 | E7: =IF(DATEDIF(C7,$B$3,"Y")=0,DATEDIF(C7,$B$3,"M")&" meses",DATEDIF(C7,$B$3,"Y")&" años y "&DATEDIF(C7,$B$3,"YM")&" meses") -> 12 años y 3 meses | F7: =IF(DATEDIF(C7,$B$3,"Y")<2,0,IF(DATEDIF(C7,$B$3,"Y")<5,0.05,IF(DATEDIF(C7,$B$3,"Y")<10,0.1,0.15))) -> 0.15 | G7: =D7*F7 -> 930000 | H7: =IF(DATE(YEAR($B$3),MONTH(C7),MIN(DAY(C7),DAY(DATE(YEAR($B$3),MONTH(C7)+1,0))))>$B$3,DATE(YEAR($B$3),MONTH(C7),MIN(DAY(C7),DAY(DATE(YEAR($B$3),MONTH(C7)+1,0)))),DATE(YEAR($B$3)+1,MONTH(C7),MIN(DAY(C7),DAY(DATE(YEAR($B$3)+1,MONTH(C7)+1,0))))) -> 46448
A8: Daniela Pardo | B8: Auxiliar | C8: 45992 | D8: 1900000 | E8: =IF(DATEDIF(C8,$B$3,"Y")=0,DATEDIF(C8,$B$3,"M")&" meses",DATEDIF(C8,$B$3,"Y")&" años y "&DATEDIF(C8,$B$3,"YM")&" meses") -> 6 meses | F8: =IF(DATEDIF(C8,$B$3,"Y")<2,0,IF(DATEDIF(C8,$B$3,"Y")<5,0.05,IF(DATEDIF(C8,$B$3,"Y")<10,0.1,0.15))) -> 0 | G8: =D8*F8 -> 0 | H8: =IF(DATE(YEAR($B$3),MONTH(C8),MIN(DAY(C8),DAY(DATE(YEAR($B$3),MONTH(C8)+1,0))))>$B$3,DATE(YEAR($B$3),MONTH(C8),MIN(DAY(C8),DAY(DATE(YEAR($B$3),MONTH(C8)+1,0)))),DATE(YEAR($B$3)+1,MONTH(C8),MIN(DAY(C8),DAY(DATE(YEAR($B$3)+1,MONTH(C8)+1,0))))) -> 46357
A9: Mateo Castillo | B9: Desarrollador | C9: 43646 | D9: 5400000 | E9: =IF(DATEDIF(C9,$B$3,"Y")=0,DATEDIF(C9,$B$3,"M")&" meses",DATEDIF(C9,$B$3,"Y")&" años y "&DATEDIF(C9,$B$3,"YM")&" meses") -> 7 años y 0 meses | F9: =IF(DATEDIF(C9,$B$3,"Y")<2,0,IF(DATEDIF(C9,$B$3,"Y")<5,0.05,IF(DATEDIF(C9,$B$3,"Y")<10,0.1,0.15))) -> 0.1 | G9: =D9*F9 -> 540000 | H9: =IF(DATE(YEAR($B$3),MONTH(C9),MIN(DAY(C9),DAY(DATE(YEAR($B$3),MONTH(C9)+1,0))))>$B$3,DATE(YEAR($B$3),MONTH(C9),MIN(DAY(C9),DAY(DATE(YEAR($B$3),MONTH(C9)+1,0)))),DATE(YEAR($B$3)+1,MONTH(C9),MIN(DAY(C9),DAY(DATE(YEAR($B$3)+1,MONTH(C9)+1,0))))) -> 46568
A10: Isabella Mora | B10: Gerente | C10: 39680 | D10: 11500000 | E10: =IF(DATEDIF(C10,$B$3,"Y")=0,DATEDIF(C10,$B$3,"M")&" meses",DATEDIF(C10,$B$3,"Y")&" años y "&DATEDIF(C10,$B$3,"YM")&" meses") -> 17 años y 10 meses | F10: =IF(DATEDIF(C10,$B$3,"Y")<2,0,IF(DATEDIF(C10,$B$3,"Y")<5,0.05,IF(DATEDIF(C10,$B$3,"Y")<10,0.1,0.15))) -> 0.15 | G10: =D10*F10 -> 1725000 | H10: =IF(DATE(YEAR($B$3),MONTH(C10),MIN(DAY(C10),DAY(DATE(YEAR($B$3),MONTH(C10)+1,0))))>$B$3,DATE(YEAR($B$3),MONTH(C10),MIN(DAY(C10),DAY(DATE(YEAR($B$3),MONTH(C10)+1,0)))),DATE(YEAR($B$3)+1,MONTH(C10),MIN(DAY(C10),DAY(DATE(YEAR($B$3)+1,MONTH(C10)+1,0))))) -> 46254
A11: Samuel Vargas | B11: Analista | C11: 45351 | D11: 3600000 | E11: =IF(DATEDIF(C11,$B$3,"Y")=0,DATEDIF(C11,$B$3,"M")&" meses",DATEDIF(C11,$B$3,"Y")&" años y "&DATEDIF(C11,$B$3,"YM")&" meses") -> 2 años y 4 meses | F11: =IF(DATEDIF(C11,$B$3,"Y")<2,0,IF(DATEDIF(C11,$B$3,"Y")<5,0.05,IF(DATEDIF(C11,$B$3,"Y")<10,0.1,0.15))) -> 0.05 | G11: =D11*F11 -> 180000 | H11: =IF(DATE(YEAR($B$3),MONTH(C11),MIN(DAY(C11),DAY(DATE(YEAR($B$3),MONTH(C11)+1,0))))>$B$3,DATE(YEAR($B$3),MONTH(C11),MIN(DAY(C11),DAY(DATE(YEAR($B$3),MONTH(C11)+1,0)))),DATE(YEAR($B$3)+1,MONTH(C11),MIN(DAY(C11),DAY(DATE(YEAR($B$3)+1,MONTH(C11)+1,0))))) -> 46446
A12: Mariana León | B12: Diseñadora | C12: 42552 | D12: 4700000 | E12: =IF(DATEDIF(C12,$B$3,"Y")=0,DATEDIF(C12,$B$3,"M")&" meses",DATEDIF(C12,$B$3,"Y")&" años y "&DATEDIF(C12,$B$3,"YM")&" meses") -> 9 años y 11 meses | F12: =IF(DATEDIF(C12,$B$3,"Y")<2,0,IF(DATEDIF(C12,$B$3,"Y")<5,0.05,IF(DATEDIF(C12,$B$3,"Y")<10,0.1,0.15))) -> 0.1 | G12: =D12*F12 -> 470000 | H12: =IF(DATE(YEAR($B$3),MONTH(C12),MIN(DAY(C12),DAY(DATE(YEAR($B$3),MONTH(C12)+1,0))))>$B$3,DATE(YEAR($B$3),MONTH(C12),MIN(DAY(C12),DAY(DATE(YEAR($B$3),MONTH(C12)+1,0)))),DATE(YEAR($B$3)+1,MONTH(C12),MIN(DAY(C12),DAY(DATE(YEAR($B$3)+1,MONTH(C12)+1,0))))) -> 46204
A13: Tomás Ríos | B13: Auxiliar | C13: 45107 | D13: 1950000 | E13: =IF(DATEDIF(C13,$B$3,"Y")=0,DATEDIF(C13,$B$3,"M")&" meses",DATEDIF(C13,$B$3,"Y")&" años y "&DATEDIF(C13,$B$3,"YM")&" meses") -> 3 años y 0 meses | F13: =IF(DATEDIF(C13,$B$3,"Y")<2,0,IF(DATEDIF(C13,$B$3,"Y")<5,0.05,IF(DATEDIF(C13,$B$3,"Y")<10,0.1,0.15))) -> 0.05 | G13: =D13*F13 -> 97500 | H13: =IF(DATE(YEAR($B$3),MONTH(C13),MIN(DAY(C13),DAY(DATE(YEAR($B$3),MONTH(C13)+1,0))))>$B$3,DATE(YEAR($B$3),MONTH(C13),MIN(DAY(C13),DAY(DATE(YEAR($B$3),MONTH(C13)+1,0)))),DATE(YEAR($B$3)+1,MONTH(C13),MIN(DAY(C13),DAY(DATE(YEAR($B$3)+1,MONTH(C13)+1,0))))) -> 46568
A14: Gabriela Sánchez | B14: Desarrolladora | C14: 40553 | D14: 7300000 | E14: =IF(DATEDIF(C14,$B$3,"Y")=0,DATEDIF(C14,$B$3,"M")&" meses",DATEDIF(C14,$B$3,"Y")&" años y "&DATEDIF(C14,$B$3,"YM")&" meses") -> 15 años y 5 meses | F14: =IF(DATEDIF(C14,$B$3,"Y")<2,0,IF(DATEDIF(C14,$B$3,"Y")<5,0.05,IF(DATEDIF(C14,$B$3,"Y")<10,0.1,0.15))) -> 0.15 | G14: =D14*F14 -> 1095000 | H14: =IF(DATE(YEAR($B$3),MONTH(C14),MIN(DAY(C14),DAY(DATE(YEAR($B$3),MONTH(C14)+1,0))))>$B$3,DATE(YEAR($B$3),MONTH(C14),MIN(DAY(C14),DAY(DATE(YEAR($B$3),MONTH(C14)+1,0)))),DATE(YEAR($B$3)+1,MONTH(C14),MIN(DAY(C14),DAY(DATE(YEAR($B$3)+1,MONTH(C14)+1,0))))) -> 46397
A15: Nicolás Peña | B15: Coordinador | C15: 44376 | D15: 5900000 | E15: =IF(DATEDIF(C15,$B$3,"Y")=0,DATEDIF(C15,$B$3,"M")&" meses",DATEDIF(C15,$B$3,"Y")&" años y "&DATEDIF(C15,$B$3,"YM")&" meses") -> 5 años y 0 meses | F15: =IF(DATEDIF(C15,$B$3,"Y")<2,0,IF(DATEDIF(C15,$B$3,"Y")<5,0.05,IF(DATEDIF(C15,$B$3,"Y")<10,0.1,0.15))) -> 0.1 | G15: =D15*F15 -> 590000 | H15: =IF(DATE(YEAR($B$3),MONTH(C15),MIN(DAY(C15),DAY(DATE(YEAR($B$3),MONTH(C15)+1,0))))>$B$3,DATE(YEAR($B$3),MONTH(C15),MIN(DAY(C15),DAY(DATE(YEAR($B$3),MONTH(C15)+1,0)))),DATE(YEAR($B$3)+1,MONTH(C15),MIN(DAY(C15),DAY(DATE(YEAR($B$3)+1,MONTH(C15)+1,0))))) -> 46567

Sheet Clientes
A1: Ejercicio 5 – Limpieza de clientes
A4: Nombre (original) | B4: Correo (original) | C4: Teléfono (original) | D4: Nombre limpio | E4: Primer apellido | F4: Usuario | G4: Dominio | H4: Teléfono normalizado | I4: Duplicado
A5: juan PÉREZ gómez | B5: juan.perez@Gmail.com | C5: 300-123 4567 | D5: =PROPER(TRIM(A5)) -> Juan Pérez Gómez | E5: =IFERROR(MID(D5,FIND(" ",D5)+1,IFERROR(FIND(" ",D5,FIND(" ",D5)+1)-FIND(" ",D5)-1,LEN(D5))),"") -> Pérez | F5: =LEFT(B5,FIND("@",B5)-1) -> juan.perez | G5: =LOWER(RIGHT(B5,LEN(B5)-FIND("@",B5))) -> gmail.com | H5: =RIGHT(SUBSTITUTE(SUBSTITUTE(SUBSTITUTE(SUBSTITUTE(SUBSTITUTE(SUBSTITUTE(SUBSTITUTE(C5," ",""),"-",""),"(",""),")",""),"+57",""),".",""),"+",""),10) -> 3001234567 | I5: =IF(SUMPRODUCT(--(UPPER($B$5:$B$16)=UPPER(B5)))>1,"SÍ","NO") -> NO
A6: maría fernanda LÓPEZ | B6: mfl88@hotmail.com | C6: (310) 555 7788 | D6: =PROPER(TRIM(A6)) -> María Fernanda López | E6: =IFERROR(MID(D6,FIND(" ",D6)+1,IFERROR(FIND(" ",D6,FIND(" ",D6)+1)-FIND(" ",D6)-1,LEN(D6))),"") -> Fernanda | F6: =LEFT(B6,FIND("@",B6)-1) -> mfl88 | G6: =LOWER(RIGHT(B6,LEN(B6)-FIND("@",B6))) -> hotmail.com | H6: =RIGHT(SUBSTITUTE(SUBSTITUTE(SUBSTITUTE(SUBSTITUTE(SUBSTITUTE(SUBSTITUTE(SUBSTITUTE(C6," ",""),"-",""),"(",""),")",""),"+57",""),".",""),"+",""),10) -> 3105557788 | I6: =IF(SUMPRODUCT(--(UPPER($B$5:$B$16)=UPPER(B6)))>1,"SÍ","NO") -> NO
A7: CARLOS andrés ruiz | B7: carlos.ruiz@empresa.co | C7: +57 315 222 3344 | D7: =PROPER(TRIM(A7)) -> Carlos Andrés Ruiz | E7: =IFERROR(MID(D7,FIND(" ",D7)+1,IFERROR(FIND(" ",D7,FIND(" ",D7)+1)-FIND(" ",D7)-1,LEN(D7))),"") -> Andrés | F7: =LEFT(B7,FIND("@",B7)-1) -> carlos.ruiz | G7: =LOWER(RIGHT(B7,LEN(B7)-FIND("@",B7))) -> empresa.co | H7: =RIGHT(SUBSTITUTE(SUBSTITUTE(SUBSTITUTE(SUBSTITUTE(SUBSTITUTE(SUBSTITUTE(SUBSTITUTE(C7," ",""),"-",""),"(",""),")",""),"+57",""),".",""),"+",""),10) -> 3152223344 | I7: =IF(SUMPRODUCT(--(UPPER($B$5:$B$16)=UPPER(B7)))>1,"SÍ","NO") -> NO
A8: ana sofía VÉLEZ | B8: ANA.VELEZ@outlook.com | C8: 3204445566 | D8: =PROPER(TRIM(A8)) -> Ana Sofía Vélez | E8: =IFERROR(MID(D8,FIND(" ",D8)+1,IFERROR(FIND(" ",D8,FIND(" ",D8)+1)-FIND(" ",D8)-1,LEN(D8))),"") -> Sofía | F8: =LEFT(B8,FIND("@",B8)-1) -> ANA.VELEZ | G8: =LOWER(RIGHT(B8,LEN(B8)-FIND("@",B8))) -> outlook.com | H8: =RIGHT(SUBSTITUTE(SUBSTITUTE(SUBSTITUTE(SUBSTITUTE(SUBSTITUTE(SUBSTITUTE(SUBSTITUTE(C8," ",""),"-",""),"(",""),")",""),"+57",""),".",""),"+",""),10) -> 3204445566 | I8: =IF(SUMPRODUCT(--(UPPER($B$5:$B$16)=UPPER(B8)))>1,"SÍ","NO") -> NO
A9: pedro ramírez | B9: pramirez@yahoo.es | C9: 301 999-0000 | D9: =PROPER(TRIM(A9)) -> Pedro Ramírez | E9: =IFERROR(MID(D9,FIND(" ",D9)+1,IFERROR(FIND(" ",D9,FIND(" ",D9)+1)-FIND(" ",D9)-1,LEN(D9))),"") -> Ramírez | F9: =LEFT(B9,FIND("@",B9)-1) -> pramirez | G9: =LOWER(RIGHT(B9,LEN(B9)-FIND("@",B9))) -> yahoo.es | H9: =RIGHT(SUBSTITUTE(SUBSTITUTE(SUBSTITUTE(SUBSTITUTE(SUBSTITUTE(SUBSTITUTE(SUBSTITUTE(C9," ",""),"-",""),"(",""),")",""),"+57",""),".",""),"+",""),10) -> 3019990000 | I9: =IF(SUMPRODUCT(--(UPPER($B$5:$B$16)=UPPER(B9)))>1,"SÍ","NO") -> NO
A10: Juan Pérez Gómez | B10: JUAN.PEREZ@gmail.com | C10: 300 123 4567 | D10: =PROPER(TRIM(A10)) -> Juan Pérez Gómez | E10: =IFERROR(MID(D10,FIND(" ",D10)+1,IFERROR(FIND(" ",D10,FIND(" ",D10)+1)-FIND(" ",D10)-1,LEN(D10))),"") -> Pérez | F10: =LEFT(B10,FIND("@",B10)-1) -> JUAN.PEREZ | G10: =LOWER(RIGHT(B10,LEN(B10)-FIND("@",B10))) -> gmail.com | H10: =RIGHT(SUBSTITUTE(SUBSTITUTE(SUBSTITUTE(SUBSTITUTE(SUBSTITUTE(SUBSTITUTE(SUBSTITUTE(C10," ",""),"-",""),"(",""),")",""),"+57",""),".",""),"+",""),10) -> 3001234567 | I10: =IF(SUMPRODUCT(--(UPPER($B$5:$B$16)=UPPER(B10)))>1,"SÍ","NO") -> NO
A11: lucía martínez ORTIZ | B11: lucia_mo@gmail.com | C11: +573118887766 | D11: =PROPER(TRIM(A11)) -> Lucía Martínez Ortiz | E11: =IFERROR(MID(D11,FIND(" ",D11)+1,IFERROR(FIND(" ",D11,FIND(" ",D11)+1)-FIND(" ",D11)-1,LEN(D11))),"") -> Martínez | F11: =LEFT(B11,FIND("@",B11)-1) -> lucia_mo | G11: =LOWER(RIGHT(B11,LEN(B11)-FIND("@",B11))) -> gmail.com | H11: =RIGHT(SUBSTITUTE(SUBSTITUTE(SUBSTITUTE(SUBSTITUTE(SUBSTITUTE(SUBSTITUTE(SUBSTITUTE(C11," ",""),"-",""),"(",""),")",""),"+57",""),".",""),"+",""),10) -> 3118887766 | I11: =IF(SUMPRODUCT(--(UPPER($B$5:$B$16)=UPPER(B11)))>1,"SÍ","NO") -> NO
A12: jorge eliécer GAITÁN | B12: jegaitan@empresa.co | C12: (312)-000-1122 | D12: =PROPER(TRIM(A12)) -> Jorge Eliécer Gaitán | E12: =IFERROR(MID(D12,FIND(" ",D12)+1,IFERROR(FIND(" ",D12,FIND(" ",D12)+1)-FIND(" ",D12)-1,LEN(D12))),"") -> Eliécer | F12: =LEFT(B12,FIND("@",B12)-1) -> jegaitan | G12: =LOWER(RIGHT(B12,LEN(B12)-FIND("@",B12))) -> empresa.co | H12: =RIGHT(SUBSTITUTE(SUBSTITUTE(SUBSTITUTE(SUBSTITUTE(SUBSTITUTE(SUBSTITUTE(SUBSTITUTE(C12," ",""),"-",""),"(",""),")",""),"+57",""),".",""),"+",""),10) -> 3120001122 | I12: =IF(SUMPRODUCT(--(UPPER($B$5:$B$16)=UPPER(B12)))>1,"SÍ","NO") -> NO
A13: valeria CANO | B13: vcano@hotmail.com | C13: 316.777.8899 | D13: =PROPER(TRIM(A13)) -> Valeria Cano | E13: =IFERROR(MID(D13,FIND(" ",D13)+1,IFERROR(FIND(" ",D13,FIND(" ",D13)+1)-FIND(" ",D13)-1,LEN(D13))),"") -> Cano | F13: =LEFT(B13,FIND("@",B13)-1) -> vcano | G13: =LOWER(RIGHT(B13,LEN(B13)-FIND("@",B13))) -> hotmail.com | H13: =RIGHT(SUBSTITUTE(SUBSTITUTE(SUBSTITUTE(SUBSTITUTE(SUBSTITUTE(SUBSTITUTE(SUBSTITUTE(C13," ",""),"-",""),"(",""),")",""),"+57",""),".",""),"+",""),10) -> 3167778899 | I13: =IF(SUMPRODUCT(--(UPPER($B$5:$B$16)=UPPER(B13)))>1,"SÍ","NO") -> NO
A14: ANA sofía vélez | B14: ana.velez@outlook.com | C14: 320 444 5566 | D14: =PROPER(TRIM(A14)) -> Ana Sofía Vélez | E14: =IFERROR(MID(D14,FIND(" ",D14)+1,IFERROR(FIND(" ",D14,FIND(" ",D14)+1)-FIND(" ",D14)-1,LEN(D14))),"") -> Sofía | F14: =LEFT(B14,FIND("@",B14)-1) -> ana.velez | G14: =LOWER(RIGHT(B14,LEN(B14)-FIND("@",B14))) -> outlook.com | H14: =RIGHT(SUBSTITUTE(SUBSTITUTE(SUBSTITUTE(SUBSTITUTE(SUBSTITUTE(SUBSTITUTE(SUBSTITUTE(C14," ",""),"-",""),"(",""),")",""),"+57",""),".",""),"+",""),10) -> 3204445566 | I14: =IF(SUMPRODUCT(--(UPPER($B$5:$B$16)=UPPER(B14)))>1,"SÍ","NO") -> NO
A15: diego alejandro mesa | B15: dmesa@unal.edu.co | C15: 3175550011 | D15: =PROPER(TRIM(A15)) -> Diego Alejandro Mesa | E15: =IFERROR(MID(D15,FIND(" ",D15)+1,IFERROR(FIND(" ",D15,FIND(" ",D15)+1)-FIND(" ",D15)-1,LEN(D15))),"") -> Alejandro | F15: =LEFT(B15,FIND("@",B15)-1) -> dmesa | G15: =LOWER(RIGHT(B15,LEN(B15)-FIND("@",B15))) -> unal.edu.co | H15: =RIGHT(SUBSTITUTE(SUBSTITUTE(SUBSTITUTE(SUBSTITUTE(SUBSTITUTE(SUBSTITUTE(SUBSTITUTE(C15," ",""),"-",""),"(",""),")",""),"+57",""),".",""),"+",""),10) -> 3175550011 | I15: =IF(SUMPRODUCT(--(UPPER($B$5:$B$16)=UPPER(B15)))>1,"SÍ","NO") -> NO
A16: paula ANDREA quintero | B16: pquintero@gmail.com | C16: +57 (300) 765 4321 | D16: =PROPER(TRIM(A16)) -> Paula Andrea Quintero | E16: =IFERROR(MID(D16,FIND(" ",D16)+1,IFERROR(FIND(" ",D16,FIND(" ",D16)+1)-FIND(" ",D16)-1,LEN(D16))),"") -> Andrea | F16: =LEFT(B16,FIND("@",B16)-1) -> pquintero | G16: =LOWER(RIGHT(B16,LEN(B16)-FIND("@",B16))) -> gmail.com | H16: =RIGHT(SUBSTITUTE(SUBSTITUTE(SUBSTITUTE(SUBSTITUTE(SUBSTITUTE(SUBSTITUTE(SUBSTITUTE(C16," ",""),"-",""),"(",""),")",""),"+57",""),".",""),"+",""),10) -> 3007654321 | I16: =IF(SUMPRODUCT(--(UPPER($B$5:$B$16)=UPPER(B16)))>1,"SÍ","NO") -> NO

Sheet E6_Ranking
A1: Ejercicio 6 – Rankings
A4: Puesto | B4: Vendedor | C4: Venta total | F4: Puesto | G4: Producto | H4: Unidades
A5: 1 | B5: =INDEX(Ventas!$C$5:$C$84,MATCH(LARGE(SUMIF(Ventas!$C$5:$C$84,Ventas!$C$5:$C$84,Ventas!$I$5:$I$84),1),SUMIF(Ventas!$C$5:$C$84,Ventas!$C$5:$C$84,Ventas!$I$5:$I$84),0)) -> Andrés Ruiz | C5: =SUMIF(Ventas!$C$5:$C$84,B5,Ventas!$I$5:$I$84) -> 29432360 | F5: =INDEX(Ventas!$G$5:$G$84,MATCH(LARGE(SUMIF(Ventas!$G$5:$G$84,Ventas!$G$5:$G$84,Ventas!$F$5:$F$84),1),SUMIF(Ventas!$G$5:$G$84,Ventas!$G$5:$G$84,Ventas!$F$5:$F$84),0)) -> Diadema USB | G5: =SUMIF(Ventas!$G$5:$G$84,F5,Ventas!$F$5:$F$84) -> 35
A6: 2 | B6: =INDEX(Ventas!$C$5:$C$84,MATCH(LARGE(SUMIF(Ventas!$C$5:$C$84,Ventas!$C$5:$C$84,Ventas!$I$5:$I$84),2),SUMIF(Ventas!$C$5:$C$84,Ventas!$C$5:$C$84,Ventas!$I$5:$I$84),0)) -> #VALUE! | C6: =SUMIF(Ventas!$C$5:$C$84,B6,Ventas!$I$5:$I$84) -> #VALUE! | F6: =INDEX(Ventas!$G$5:$G$84,MATCH(LARGE(SUMIF(Ventas!$G$5:$G$84,Ventas!$G$5:$G$84,Ventas!$F$5:$F$84),2),SUMIF(Ventas!$G$5:$G$84,Ventas!$G$5:$G$84,Ventas!$F$5:$F$84),0)) -> #VALUE! | G6: =SUMIF(Ventas!$G$5:$G$84,F6,Ventas!$F$5:$F$84) -> #VALUE!
A7: 3 | B7: =INDEX(Ventas!$C$5:$C$84,MATCH(LARGE(SUMIF(Ventas!$C$5:$C$84,Ventas!$C$5:$C$84,Ventas!$I$5:$I$84),3),SUMIF(Ventas!$C$5:$C$84,Ventas!$C$5:$C$84,Ventas!$I$5:$I$84),0)) -> #VALUE! | C7: =SUMIF(Ventas!$C$5:$C$84,B7,Ventas!$I$5:$I$84) -> #VALUE! | F7: =INDEX(Ventas!$G$5:$G$84,MATCH(LARGE(SUMIF(Ventas!$G$5:$G$84,Ventas!$G$5:$G$84,Ventas!$F$5:$F$84),3),SUMIF(Ventas!$G$5:$G$84,Ventas!$G$5:$G$84,Ventas!$F$5:$F$84),0)) -> #VALUE! | G7: =SUMIF(Ventas!$G$5:$G$84,F7,Ventas!$F$5:$F$84) -> #VALUE!

Sheet Festivos
A1: Festivos Colombia 2026
A2: Usar como rango de festivos en el ejercicio 7.
A4: Fecha | B4: Festivo
A5: 46023 | B5: Año Nuevo
A6: 46034 | B6: Reyes Magos
A7: 46104 | B7: San José
A8: 46114 | B8: Jueves Santo
A9: 46115 | B9: Viernes Santo
A10: 46143 | B10: Día del Trabajo
A11: 46160 | B11: Ascensión
A12: 46181 | B12: Corpus Christi
A13: 46188 | B13: Sagrado Corazón
A14: 46202 | B14: San Pedro y San Pablo
A15: 46223 | B15: Independencia
A16: 46241 | B16: Batalla de Boyacá
... A22: 46381 | B22: Navidad

Sheet Pedidos
A1: Ejercicio 7 – Entregas
A4: Pedido | B4: Región | C4: Fecha pedido | D4: Plazo (días hábiles) | E4: Fecha entrega real | F4: Fecha límite | G4: Días hábiles reales | H4: Estado | J4: Retrasos por región
A5: PED-500 | B5: Caribe | C5: 46115 | D5: 8 | E5: 46128 | F5: =WORKDAY(C5,D5,Festivos!$A$5:$A$22) -> 46127 | G5: =IF(E5="","",NETWORKDAYS(C5,E5,Festivos!$A$5:$A$22)) -> 9 | H5: =IF(E5="","Pendiente",IF(E5>F5,"Retrasado","A tiempo")) -> Retrasado | J5: Región | K5: Retrasados
A6: PED-501 | B6: Andina | C6: 46167 | D6: 3 | E6: 46170 | F6: =WORKDAY(C6,D6,Festivos!$A$5:$A$22) -> 46170 | G6: =IF(E6="","",NETWORKDAYS(C6,E6,Festivos!$A$5:$A$22)) -> 4 | H6: =IF(E6="","Pendiente",IF(E6>F6,"Retrasado","A tiempo")) -> A tiempo | J6: Andina | K6: =COUNTIFS($B$5:$B$22,"Andina",$H$5:$H$22,"Retrasado") -> 2
A7: PED-502 | B7: Caribe | C7: 46111 | D7: 3 | E7: 46120 | F7: =WORKDAY(C7,D7,Festivos!$A$5:$A$22) -> 46118 | G7: =IF(E7="","",NETWORKDAYS(C7,E7,Festivos!$A$5:$A$22)) -> 6 | H7: =IF(E7="","Pendiente",IF(E7>F7,"Retrasado","A tiempo")) -> Retrasado | J7: Caribe | K7: =COUNTIFS($B$5:$B$22,"Caribe",$H$5:$H$22,"Retrasado") -> 6
A8: PED-503 | B8: Caribe | C8: 46125 | D8: 2 | E8: 46131 | F8: =WORKDAY(C8,D8,Festivos!$A$5:$A$22) -> 46127 | G8: =IF(E8="","",NETWORKDAYS(C8,E8,Festivos!$A$5:$A$22)) -> 5 | H8: =IF(E8="","Pendiente",IF(E8>F8,"Retrasado","A tiempo")) -> Retrasado | J8: Pacífico | K8: =COUNTIFS($B$5:$B$22,"Pacífico",$H$5:$H$22,"Retrasado") -> 0
A9: PED-504 | B9: Pacífico | C9: 46134 | D9: 3 | F9: =WORKDAY(C9,D9,Festivos!$A$5:$A$22) -> 46139 | G9: =IF(E9="","",NETWORKDAYS(C9,E9,Festivos!$A$5:$A$22)) | H9: =IF(E9="","Pendiente",IF(E9>F9,"Retrasado","A tiempo")) -> Pendiente | J9: Orinoquía | K9: =COUNTIFS($B$5:$B$22,"Orinoquía",$H$5:$H$22,"Retrasado") -> 1
A10: PED-505 | B10: Andina | C10: 46132 | D10: 8 | E10: 46142 | F10: =WORKDAY(C10,D10,Festivos!$A$5:$A$22) -> 46142 | G10: =IF(E10="","",NETWORKDAYS(C10,E10,Festivos!$A$5:$A$22)) -> 9 | H10: =IF(E10="","Pendiente",IF(E10>F10,"Retrasado","A tiempo")) -> A tiempo
A11: PED-506 | B11: Caribe | C11: 46142 | D11: 8 | E11: 46156 | F11: =WORKDAY(C11,D11,Festivos!$A$5:$A$22) -> 46155 | G11: =IF(E11="","",NETWORKDAYS(C11,E11,Festivos!$A$5:$A$22)) -> 10 | H11: =IF(E11="","Pendiente",IF(E11>F11,"Retrasado","A tiempo")) -> Retrasado
A12: PED-507 | B12: Orinoquía | C12: 46167 | D12: 3 | E12: 46170 | F12: =WORKDAY(C12,D12,Festivos!$A$5:$A$22) -> 46170 | G12: =IF(E12="","",NETWORKDAYS(C12,E12,Festivos!$A$5:$A$22)) -> 4 | H12: =IF(E12="","Pendiente",IF(E12>F12,"Retrasado","A tiempo")) -> A tiempo
A13: PED-508 | B13: Caribe | C13: 46120 | D13: 2 | E13: 46124 | F13: =WORKDAY(C13,D13,Festivos!$A$5:$A$22) -> 46122 | G13: =IF(E13="","",NETWORKDAYS(C13,E13,Festivos!$A$5:$A$22)) -> 3 | H13: =IF(E13="","Pendiente",IF(E13>F13,"Retrasado","A tiempo")) -> Retrasado
A14: PED-509 | B14: Andina | C14: 46115 | D14: 8 | E14: 46124 | F14: =WORKDAY(C14,D14,Festivos!$A$5:$A$22) -> 46127 | G14: =IF(E14="","",NETWORKDAYS(C14,E14,Festivos!$A$5:$A$22)) -> 5 | H14: =IF(E14="","Pendiente",IF(E14>F14,"Retrasado","A tiempo")) -> A tiempo
A15: PED-510 | B15: Andina | C15: 46139 | D15: 8 | E15: 46148 | F15: =WORKDAY(C15,D15,Festivos!$A$5:$A$22) -> 46150 | G15: =IF(E15="","",NETWORKDAYS(C15,E15,Festivos!$A$5:$A$22)) -> 7 | H15: =IF(E15="","Pendiente",IF(E15>F15,"Retrasado","A tiempo")) -> A tiempo
A16: PED-511 | B16: Pacífico | C16: 46128 | D16: 3 | F16: =WORKDAY(C16,D16,Festivos!$A$5:$A$22) -> 46133 | G16: =IF(E16="","",NETWORKDAYS(C16,E16,Festivos!$A$5:$A$22)) | H16: =IF(E16="","Pendiente",IF(E16>F16,"Retrasado","A tiempo")) -> Pendiente
A17: PED-512 | B17: Andina | C17: 46104 | D17: 2 | E17: 46113 | F17: =WORKDAY(C17,D17,Festivos!$A$5:$A$22) -> 46106 | G17: =IF(E17="","",NETWORKDAYS(C17,E17,Festivos!$A$5:$A$22)) -> 7 | H17: =IF(E17="","Pendiente",IF(E17>F17,"Retrasado","A tiempo")) -> Retrasado
A18: PED-513 | B18: Caribe | C18: 46105 | D18: 8 | E18: 46118 | F18: =WORKDAY(C18,D18,Festivos!$A$5:$A$22) -> 46119 | G18: =IF(E18="","",NETWORKDAYS(C18,E18,Festivos!$A$5:$A$22)) -> 8 | H18: =IF(E18="","Pendiente",IF(E18>F18,"Retrasado","A tiempo")) -> A tiempo
A19: PED-514 | B19: Caribe | C19: 46132 | D19: 8 | E19: 46147 | F19: =WORKDAY(C19,D19,Festivos!$A$5:$A$22) -> 46142 | G19: =IF(E19="","",NETWORKDAYS(C19,E19,Festivos!$A$5:$A$22)) -> 11 | H19: =IF(E19="","Pendiente",IF(E19>F19,"Retrasado","A tiempo")) -> Retrasado
A20: PED-515 | B20: Orinoquía | C20: 46163 | D20: 5 | E20: 46171 | F20: =WORKDAY(C20,D20,Festivos!$A$5:$A$22) -> 46170 | G20: =IF(E20="","",NETWORKDAYS(C20,E20,Festivos!$A$5:$A$22)) -> 7 | H20: =IF(E20="","Pendiente",IF(E20>F20,"Retrasado","A tiempo")) -> Retrasado
A21: PED-516 | B21: Andina | C21: 46114 | D21: 8 | F21: =WORKDAY(C21,D21,Festivos!$A$5:$A$22) -> 46127 | G21: =IF(E21="","",NETWORKDAYS(C21,E21,Festivos!$A$5:$A$22)) | H21: =IF(E21="","Pendiente",IF(E21>F21,"Retrasado","A tiempo")) -> Pendiente
A22: PED-517 | B22: Andina | C22: 46147 | D22: 8 | E22: 46160 | F22: =WORKDAY(C22,D22,Festivos!$A$5:$A$22) -> 46157 | G22: =IF(E22="","",NETWORKDAYS(C22,E22,Festivos!$A$5:$A$22)) -> 9 | H22: =IF(E22="","Pendiente",IF(E22>F22,"Retrasado","A tiempo")) -> Retrasado

Sheet E9_Panel
A1: Ejercicio 9 – Panel interactivo
A4: Vendedor | B4: Laura Gómez
A5: Mes | B5: 1
A7: Venta total | B7: =SUMIFS(Ventas!$I$5:$I$84,Ventas!$C$5:$C$84,$B$4,Ventas!$B$5:$B$84,">="&DATE(2026,$B$5,1),Ventas!$B$5:$B$84,"<"&DATE(2026,$B$5+1,1)) -> 25309800
A8: Unidades vendidas | B8: =SUMIFS(Ventas!$F$5:$F$84,Ventas!$C$5:$C$84,$B$4,Ventas!$B$5:$B$84,">="&DATE(2026,$B$5,1),Ventas!$B$5:$B$84,"<"&DATE(2026,$B$5+1,1)) -> 14
A9: Transacciones | B9: =COUNTIFS(Ventas!$C$5:$C$84,$B$4,Ventas!$B$5:$B$84,">="&DATE(2026,$B$5,1),Ventas!$B$5:$B$84,"<"&DATE(2026,$B$5+1,1)) -> 4
A10: Ticket promedio | B10: =IF(B9=0,0,B7/B9) -> 6327450
A11: Producto más vendido | B11: =IFERROR(INDEX(Ventas!$G$5:$G$84,MATCH(MAX(IF((Ventas!$C$5:$C$84=$B$4)*(MONTH(Ventas!$B$5:$B$84)=$B$5),Ventas!$F$5:$F$84)),IF((Ventas!$C$5:$C$84=$B$4)*(MONTH(Ventas!$B$5:$B$84)=$B$5),Ventas!$F$5:$F$84),0)),"")
A12: Variación vs. mes anterior | B12: =IF($B$5=1,"N/A",IFERROR((B7-SUMIFS(Ventas!$I$5:$I$84,Ventas!$C$5:$C$84,$B$4,Ventas!$B$5:$B$84,">="&DATE(2026,$B$5-1,1),Ventas!$B$5:$B$84,"<"&DATE(2026,$B$5,1)))/SUMIFS(Ventas!$I$5:$I$84,Ventas!$C$5:$C$84,$B$4,Ventas!$B$5:$B$84,">="&DATE(2026,$B$5-1,1),Ventas!$B$5:$B$84,"<"&DATE(2026,$B$5,1)),"N/A")) -> N/A

Sheet E10_Credito
A1: Ejercicio 10 – Crédito de libre inversión
A3: Monto del crédito | B3: 25000000
A4: Tasa efectiva anual | B4: 0.245
A5: Plazo (meses) | B5: 36
A6: Tasa mensual equivalente | B6: =(1+B4)^(1/12)-1 -> 0.018429051
A7: Cuota fija | B7: =PMT(B6,B5,-B3) -> 956247.5
A8: Escenario B: abono extra | B8: 6000000
A9: Escenario B: mes del abono | B9: 10
A10: Escenario B: meses ahorrados | B10: =COUNTIF(F14:F49,">0")-COUNTIF(N14:N49,">0") -> 9
A11: Escenario B: intereses ahorrados | B11: =SUM(D14:D49)-SUM(K14:K49) -> 2926429.8
A13: Mes | B13: Saldo inicial | C13: Cuota | D13: Interés | E13: Abono a capital | F13: Saldo final | H13: Mes | I13: Saldo inicial | J13: Cuota | K13: Interés | L13: Abono a capital | M13: Abono extra | N13: Saldo final
A14: 1 | B14: =$B$3 -> 25000000 | C14: =$B$7 -> 956247.5 | D14: =B14*$B$6 -> 460726.28 | E14: =C14-D14 -> 495521.22 | F14: =MAX(0,B14-E14) -> 24504479 | H14: 1 | I14: =$B$3 -> 25000000 | J14: =IF(I14<=0,0,$B$7) -> 956247.5 | K14: =IF(I14<=0,0,I14*$B$6) -> 460726.28 | L14: =IF(I14<=0,0,MIN(J14-K14,I14)) -> 495521.22 | M14: =IF(AND(H14=$B$9,I14>0),$B$8,0) -> 0 | N14: =MAX(0,I14-L14-M14) -> 24504479
A15: 2 | B15: =F14 -> 24504479 | C15: =$B$7 -> 956247.5 | D15: =B15*$B$6 -> 451594.29 | E15: =C15-D15 -> 504653.21 | F15: =MAX(0,B15-E15) -> 23999826 | H15: 2 | I15: =N14 -> 24504479 | J15: =IF(I15<=0,0,$B$7) -> 956247.5 | K15: =IF(I15<=0,0,I15*$B$6) -> 451594.29 | L15: =IF(I15<=0,0,MIN(J15-K15,I15)) -> 504653.21 | M15: =IF(AND(H15=$B$9,I15>0),$B$8,0) -> 0 | N15: =MAX(0,I15-L15-M15) -> 23999826
A16: 3 | B16: =F15 -> 23999826 | C16: =$B$7 -> 956247.5 | D16: =B16*$B$6 -> 442294.01 | E16: =C16-D16 -> 513953.49 | F16: =MAX(0,B16-E16) -> 23485872 | H16: 3 | I16: =N15 -> 23999826 | J16: =IF(I16<=0,0,$B$7) -> 956247.5 | K16: =IF(I16<=0,0,I16*$B$6) -> 442294.01 | L16: =IF(I16<=0,0,MIN(J16-K16,I16)) -> 513953.49 | M16: =IF(AND(H16=$B$9,I16>0),$B$8,0) -> 0 | N16: =MAX(0,I16-L16-M16) -> 23485872
A17: 4 | B17: =F16 -> 23485872 | C17: =$B$7 -> 956247.5 | D17: =B17*$B$6 -> 432822.34 | E17: =C17-D17 -> 523425.16 | F17: =MAX(0,B17-E17) -> 22962447 | H17: 4 | I17: =N16 -> 23485872 | J17: =IF(I17<=0,0,$B$7) -> 956247.5 | K17: =IF(I17<=0,0,I17*$B$6) -> 432822.34 | L17: =IF(I17<=0,0,MIN(J17-K17,I17)) -> 523425.16 | M17: =IF(AND(H17=$B$9,I17>0),$B$8,0) -> 0 | N17: =MAX(0,I17-L17-M17) -> 22962447
A18: 5 | B18: =F17 -> 22962447 | C18: =$B$7 -> 956247.5 | D18: =B18*$B$6 -> 423176.11 | E18: =C18-D18 -> 533071.39 | F18: =MAX(0,B18-E18) -> 22429376 | H18: 5 | I18: =N17 -> 22962447 | J18: =IF(I18<=0,0,$B$7) -> 956247.5 | K18: =IF(I18<=0,0,I18*$B$6) -> 423176.11 | L18: =IF(I18<=0,0,MIN(J18-K18,I18)) -> 533071.39 | M18: =IF(AND(H18=$B$9,I18>0),$B$8,0) -> 0 | N18: =MAX(0,I18-L18-M18) -> 22429376
A19: 6 | B19: =F18 -> 22429376 | C19: =$B$7 -> 956247.5 | D19: =B19*$B$6 -> 413352.11 | E19: =C19-D19 -> 542895.39 | F19: =MAX(0,B19-E19) -> 21886480 | H19: 6 | I19: =N18 -> 22429376 | J19: =IF(I19<=0,0,$B$7) -> 956247.5 | K19: =IF(I19<=0,0,I19*$B$6) -> 413352.11 | L19: =IF(I19<=0,0,MIN(J19-K19,I19)) -> 542895.39 | M19: =IF(AND(H19=$B$9,I19>0),$B$8,0) -> 0 | N19: =MAX(0,I19-L19-M19) -> 21886480
A20: 7 | B20: =F19 -> 21886480 | C20: =$B$7 -> 956247.5 | D20: =B20*$B$6 -> 403347.06 | E20: =C20-D20 -> 552900.44 | F20: =MAX(0,B20-E20) -> 21333580 | H20: 7 | I20: =N19 -> 21886480 | J20: =IF(I20<=0,0,$B$7) -> 956247.5 | K20: =IF(I20<=0,0,I20*$B$6) -> 403347.06 | L20: =IF(I20<=0,0,MIN(J20-K20,I20)) -> 552900.44 | M20: =IF(AND(H20=$B$9,I20>0),$B$8,0) -> 0 | N20: =MAX(0,I20-L20-M20) -> 21333580
A21: 8 | B21: =F20 -> 21333580 | C21: =$B$7 -> 956247.5 | D21: =B21*$B$6 -> 393157.63 | E21: =C21-D21 -> 563089.87 | F21: =MAX(0,B21-E21) -> 20770490 | H21: 8 | I21: =N20 -> 21333580 | J21: =IF(I21<=0,0,$B$7) -> 956247.5 | K21: =IF(I21<=0,0,I21*$B$6) -> 393157.63 | L21: =IF(I21<=0,0,MIN(J21-K21,I21)) -> 563089.87 | M21: =IF(AND(H21=$B$9,I21>0),$B$8,0) -> 0 | N21: =MAX(0,I21-L21-M21) -> 20770490
A22: 9 | B22: =F21 -> 20770490 | C22: =$B$7 -> 956247.5 | D22: =B22*$B$6 -> 382780.42 | E22: =C22-D22 -> 573467.08 | F22: =MAX(0,B22-E22) -> 20197023 | H22: 9 | I22: =N21 -> 20770490 | J22: =IF(I22<=0,0,$B$7) -> 956247.5 | K22: =IF(I22<=0,0,I22*$B$6) -> 382780.42 | L22: =IF(I22<=0,0,MIN(J22-K22,I22)) -> 573467.08 | M22: =IF(AND(H22=$B$9,I22>0),$B$8,0) -> 0 | N22: =MAX(0,I22-L22-M22) -> 20197023
A23: 10 | B23: =F22 -> 20197023 | C23: =$B$7 -> 956247.5 | D23: =B23*$B$6 -> 372211.97 | E23: =C23-D23 -> 584035.54 | F23: =MAX(0,B23-E23) -> 19612987 | H23: 10 | I23: =N22 -> 20197023 | J23: =IF(I23<=0,0,$B$7) -> 956247.5 | K23: =IF(I23<=0,0,I23*$B$6) -> 372211.97 | L23: =IF(I23<=0,0,MIN(J23-K23,I23)) -> 584035.54 | M23: =IF(AND(H23=$B$9,I23>0),$B$8,0) -> 6000000 | N23: =MAX(0,I23-L23-M23) -> 13612987
A24: 11 | B24: =F23 -> 19612987 | C24: =$B$7 -> 956247.5 | D24: =B24*$B$6 -> 361448.75 | E24: =C24-D24 -> 594798.76 | F24: =MAX(0,B24-E24) -> 19018188 | H24: 11 | I24: =N23 -> 13612987 | J24: =IF(I24<=0,0,$B$7) -> 956247.5 | K24: =IF(I24<=0,0,I24*$B$6) -> 250874.44 | L24: =IF(I24<=0,0,MIN(J24-K24,I24)) -> 705373.06 | M24: =IF(AND(H24=$B$9,I24>0),$B$8,0) -> 0 | N24: =MAX(0,I24-L24-M24) -> 12907614
A25: 12 | B25: =F24 -> 19018188 | C25: =$B$7 -> 956247.5 | D25: =B25*$B$6 -> 350487.17 | E25: =C25-D25 -> 605760.33 | F25: =MAX(0,B25-E25) -> 18412428 | H25: 12 | I25: =N24 -> 12907614 | J25: =IF(I25<=0,0,$B$7) -> 956247.5 | K25: =IF(I25<=0,0,I25*$B$6) -> 237875.08 | L25: =IF(I25<=0,0,MIN(J25-K25,I25)) -> 718372.42 | M25: =IF(AND(H25=$B$9,I25>0),$B$8,0) -> 0 | N25: =MAX(0,I25-L25-M25) -> 12189242
A26: 13 | B26: =F25 -> 18412428 | C26: =$B$7 -> 956247.5 | D26: =B26*$B$6 -> 339323.58 | E26: =C26-D26 -> 616923.92 | F26: =MAX(0,B26-E26) -> 17795504 | H26: 13 | I26: =N25 -> 12189242 | J26: =IF(I26<=0,0,$B$7) -> 956247.5 | K26: =IF(I26<=0,0,I26*$B$6) -> 224636.16 | L26: =IF(I26<=0,0,MIN(J26-K26,I26)) -> 731611.34 | M26: =IF(AND(H26=$B$9,I26>0),$B$8,0) -> 0 | N26: =MAX(0,I26-L26-M26) -> 11457630
... A49: 36 | B49: =F48 -> 938943.66 | C49: =$B$7 -> 956247.5 | D49: =B49*$B$6 -> 17303.841 | E49: =C49-D49 -> 938943.66 | F49: =MAX(0,B49-E49) -> 0 | H49: 36 | I49: =N48 -> 0 | J49: =IF(I49<=0,0,$B$7) -> 0 | K49: =IF(I49<=0,0,I49*$B$6) -> 0 | L49: =IF(I49<=0,0,MIN(J49-K49,I49)) -> 0 | M49: =IF(AND(H49=$B$9,I49>0),$B$8,0) -> 0 | N49: =MAX(0,I49-L49-M49) -> 0
